{"measurements": {"time_seconds": "23.570361"}, "metadata": {"benchmark": "pennant_fast.rg", "argv": ["pennant.tests/sedovbig3x30/sedovbig.pnt", "-seq_init", "0", "-par_init", "1", "-print_ts", "1", "-prune", "5", "-npieces", "2", "-numpcx", "1", "-numpcy", "2", "-ll:csize", "8192", "-ll:cpu", "2", "-fflow-spmd-shardsize", "2", "-fvectorize-unsafe", "1"], "host": "n0004.sapling.stanford.edu", "branch": "master", "date": "2017-10-12T20:44:00.246011", "commit": "a0b664240da0f411f8b125b58d73cf3effb88069"}}