{"measurements": {"time_seconds": "38.915489"}, "metadata": {"benchmark": "pennant_fast.rg", "argv": ["pennant.tests/sedovbig3x30/sedovbig.pnt", "-seq_init", "0", "-par_init", "1", "-print_ts", "1", "-prune", "5", "-npieces", "2", "-numpcx", "1", "-numpcy", "2", "-ll:csize", "8192", "-ll:cpu", "2", "-fflow-spmd-shardsize", "2", "-fvectorize-unsafe", "1"], "host": "n0004.sapling.stanford.edu", "branch": "master", "date": "2017-09-18T19:24:44.622569", "commit": "16912e9c4bca014b2df67f50085caf36479f57aa"}}