{"measurements": {"time_seconds": "25.971292"}, "metadata": {"benchmark": "pennant_fast.rg", "argv": ["pennant.tests/sedovbig3x30/sedovbig.pnt", "-seq_init", "0", "-par_init", "1", "-print_ts", "1", "-prune", "5", "-npieces", "2", "-numpcx", "1", "-numpcy", "2", "-ll:csize", "8192", "-ll:cpu", "2", "-fflow-spmd-shardsize", "2", "-fvectorize-unsafe", "1"], "host": "n0004.sapling.stanford.edu", "branch": "subprocess", "date": "2018-03-08T22:09:48.995420", "commit": "332c64916836a32302017c095b956c02fd127330", "nodes": 1}}