{"measurements": {"time_seconds": "32.252675"}, "metadata": {"benchmark": "pennant_fast.rg", "argv": ["pennant.tests/sedovbig3x30/sedovbig.pnt", "-seq_init", "0", "-par_init", "1", "-print_ts", "1", "-prune", "5", "-npieces", "2", "-numpcx", "1", "-numpcy", "2", "-ll:csize", "8192", "-ll:cpu", "2", "-fflow-spmd-shardsize", "2", "-fvectorize-unsafe", "1"], "host": "n0004.sapling.stanford.edu", "branch": "control_replication", "date": "2018-01-09T06:13:35.792619", "commit": "67a783a5a1bc658003e0bed75ece95557460e86a", "nodes": 1}}