{"measurements": {"time_seconds": "32.385956"}, "metadata": {"benchmark": "pennant_fast.rg", "argv": ["pennant.tests/sedovbig3x30/sedovbig.pnt", "-seq_init", "0", "-par_init", "1", "-print_ts", "1", "-prune", "5", "-npieces", "2", "-numpcx", "1", "-numpcy", "2", "-ll:csize", "8192", "-ll:cpu", "2", "-fflow-spmd-shardsize", "2", "-fvectorize-unsafe", "1"], "host": "n0004.sapling.stanford.edu", "branch": "python", "date": "2018-02-09T23:09:44.261297", "commit": "66a9dd1dd912a5fc878eea95fb4c7c3513d1ad89", "nodes": 1}}